[
    {
        "word": "熱",
        "count": 1,
        "total_count": 16,
        "x": -7.929000377655029,
        "y": -0.490597665309906,
        "color": "#388004"
    },
    {
        "word": "コロナ",
        "count": 1,
        "total_count": 977,
        "x": 3.846348524093628,
        "y": -17.236757278442383,
        "color": "red"
    },
    {
        "word": "なん",
        "count": 1,
        "total_count": 22,
        "x": -4.144083499908447,
        "y": -9.87752628326416,
        "color": "#05ffa6"
    },
    {
        "word": "ら",
        "count": 1,
        "total_count": 15,
        "x": 0.25382012128829956,
        "y": -4.002724647521973,
        "color": "#ac4f06"
    }
]