[
    {
        "word": "政府",
        "count": 1,
        "total_count": 39,
        "x": -1.6724395751953125,
        "y": 10.529287338256836,
        "color": "#69d84f"
    },
    {
        "word": "こと",
        "count": 1,
        "total_count": 160,
        "x": -8.478551864624023,
        "y": 6.100689888000488,
        "color": "#388004"
    },
    {
        "word": "武漢",
        "count": 2,
        "total_count": 98,
        "x": 4.055424690246582,
        "y": 14.652351379394531,
        "color": "red"
    },
    {
        "word": "これ",
        "count": 1,
        "total_count": 69,
        "x": -6.52756404876709,
        "y": -1.6282962560653687,
        "color": "red"
    },
    {
        "word": "桜",
        "count": 2,
        "total_count": 29,
        "x": 13.792736053466797,
        "y": -10.366863250732422,
        "color": "red"
    },
    {
        "word": "他",
        "count": 1,
        "total_count": 14,
        "x": -0.2102670669555664,
        "y": 0.06203742325305939,
        "color": "#388004"
    },
    {
        "word": "事",
        "count": 1,
        "total_count": 113,
        "x": -8.554739952087402,
        "y": 6.119753360748291,
        "color": "#388004"
    },
    {
        "word": "いい",
        "count": 1,
        "total_count": 77,
        "x": -9.006982803344727,
        "y": -10.00387954711914,
        "color": "#05ffa6"
    },
    {
        "word": "野党",
        "count": 1,
        "total_count": 15,
        "x": -3.899357318878174,
        "y": 10.292577743530273,
        "color": "#ca9bf7"
    },
    {
        "word": "コロナ",
        "count": 1,
        "total_count": 977,
        "x": 3.846348524093628,
        "y": -17.236757278442383,
        "color": "red"
    },
    {
        "word": "何",
        "count": 1,
        "total_count": 68,
        "x": -8.305984497070312,
        "y": -5.79446268081665,
        "color": "#05ffa6"
    },
    {
        "word": "みたい",
        "count": 1,
        "total_count": 45,
        "x": -5.0331854820251465,
        "y": -13.050077438354492,
        "color": "#05ffa6"
    },
    {
        "word": "化",
        "count": 1,
        "total_count": 26,
        "x": -2.2421207427978516,
        "y": 17.092390060424805,
        "color": "#997570"
    }
]