[
    {
        "word": "明日",
        "count": 1,
        "total_count": 41,
        "x": 4.7192182540893555,
        "y": 16.15350914001465,
        "color": "#054907"
    },
    {
        "word": "どこ",
        "count": 1,
        "total_count": 22,
        "x": 12.092702865600586,
        "y": -3.9633686542510986,
        "color": "#ff964f"
    },
    {
        "word": "コロナ",
        "count": 1,
        "total_count": 977,
        "x": 20.82737922668457,
        "y": 4.147772789001465,
        "color": "#acbb0d"
    },
    {
        "word": "蔓延",
        "count": 1,
        "total_count": 32,
        "x": -5.698538303375244,
        "y": -10.046252250671387,
        "color": "#fcfc81"
    },
    {
        "word": "怖い",
        "count": 1,
        "total_count": 75,
        "x": 18.17124366760254,
        "y": 2.2313032150268555,
        "color": "#acbb0d"
    }
]