[
    {
        "word": "感染症",
        "count": 1,
        "total_count": 19,
        "x": -12.152274131774902,
        "y": -7.856927394866943,
        "color": "#7bfdc7"
    },
    {
        "word": "日本",
        "count": 1,
        "total_count": 166,
        "x": -6.898014068603516,
        "y": -1.0123347043991089,
        "color": "#befdb7"
    },
    {
        "word": "コロナウイルス",
        "count": 1,
        "total_count": 293,
        "x": -17.35605812072754,
        "y": -6.746431350708008,
        "color": "#a90308"
    },
    {
        "word": "皆様",
        "count": 1,
        "total_count": 17,
        "x": 15.258275985717773,
        "y": 11.113725662231445,
        "color": "#983fb2"
    }
]