[
    {
        "word": "朝",
        "count": 1,
        "total_count": 18,
        "x": 2.3389925956726074,
        "y": 15.81421947479248,
        "color": "#054907"
    },
    {
        "word": "コロナ",
        "count": 2,
        "total_count": 977,
        "x": 20.82737922668457,
        "y": 4.147772789001465,
        "color": "#acbb0d"
    },
    {
        "word": "人",
        "count": 1,
        "total_count": 216,
        "x": -0.2386651188135147,
        "y": -7.278883457183838,
        "color": "#ff6cb5"
    },
    {
        "word": "感染者",
        "count": 1,
        "total_count": 63,
        "x": -14.811662673950195,
        "y": -0.008791374042630196,
        "color": "#430541"
    },
    {
        "word": "情報",
        "count": 1,
        "total_count": 38,
        "x": -2.3098607063293457,
        "y": -8.41650676727295,
        "color": "#ff6cb5"
    },
    {
        "word": "いい",
        "count": 1,
        "total_count": 77,
        "x": 16.443626403808594,
        "y": -2.109023094177246,
        "color": "#4efd54"
    },
    {
        "word": "俺",
        "count": 1,
        "total_count": 23,
        "x": 15.484210014343262,
        "y": 2.7147741317749023,
        "color": "#acbb0d"
    }
]