[
    {
        "word": "予定",
        "count": 1,
        "total_count": 30,
        "x": -2.5316450595855713,
        "y": 10.31760025024414,
        "color": "#0804f9"
    },
    {
        "word": "中",
        "count": 2,
        "total_count": 73,
        "x": 3.066070556640625,
        "y": -1.1008296012878418,
        "color": "#7ea07a"
    },
    {
        "word": "市",
        "count": 2,
        "total_count": 24,
        "x": -0.4258944094181061,
        "y": 4.005334854125977,
        "color": "#fafe4b"
    },
    {
        "word": "新型コロナウィルス",
        "count": 1,
        "total_count": 83,
        "x": -15.489548683166504,
        "y": -4.686130523681641,
        "color": "#2bb179"
    },
    {
        "word": "影響",
        "count": 1,
        "total_count": 132,
        "x": 2.1171457767486572,
        "y": 1.081254005432129,
        "color": "#fafe4b"
    },
    {
        "word": "延期",
        "count": 1,
        "total_count": 30,
        "x": -5.594666957855225,
        "y": 12.110272407531738,
        "color": "#0804f9"
    },
    {
        "word": "イベント",
        "count": 1,
        "total_count": 21,
        "x": -1.870368480682373,
        "y": 11.916138648986816,
        "color": "#876e4b"
    }
]