[
    {
        "word": "コロナ",
        "count": 1,
        "total_count": 977,
        "x": 3.846348524093628,
        "y": -17.236757278442383,
        "color": "red"
    },
    {
        "word": "みたい",
        "count": 1,
        "total_count": 45,
        "x": -5.0331854820251465,
        "y": -13.050077438354492,
        "color": "#05ffa6"
    },
    {
        "word": "東京",
        "count": 1,
        "total_count": 35,
        "x": 8.928055763244629,
        "y": -0.4774792790412903,
        "color": "#388004"
    },
    {
        "word": "ない",
        "count": 2,
        "total_count": 165,
        "x": -12.52199935913086,
        "y": -4.814731597900391,
        "color": "#65ab7c"
    },
    {
        "word": "店",
        "count": 1,
        "total_count": 79,
        "x": 8.211161613464355,
        "y": -4.2682390213012695,
        "color": "#ff0789"
    },
    {
        "word": "ところ",
        "count": 1,
        "total_count": 29,
        "x": -5.612021446228027,
        "y": 0.18708942830562592,
        "color": "#388004"
    }
]