[
    {
        "word": "花粉症",
        "count": 1,
        "total_count": 24,
        "x": -14.209364891052246,
        "y": 10.454093933105469,
        "color": "#a6c875"
    },
    {
        "word": "コロナ",
        "count": 1,
        "total_count": 977,
        "x": 3.846348524093628,
        "y": -17.236757278442383,
        "color": "red"
    },
    {
        "word": "影響",
        "count": 1,
        "total_count": 132,
        "x": 1.7583144903182983,
        "y": 1.247840166091919,
        "color": "#388004"
    },
    {
        "word": "店",
        "count": 1,
        "total_count": 79,
        "x": 8.211161613464355,
        "y": -4.2682390213012695,
        "color": "#ff0789"
    }
]