[
    {
        "word": "今年",
        "count": 1,
        "total_count": 22,
        "x": 13.342610359191895,
        "y": -9.6392822265625,
        "color": "red"
    },
    {
        "word": "楽しみ",
        "count": 1,
        "total_count": 20,
        "x": 2.2852044105529785,
        "y": -13.614408493041992,
        "color": "#7d7103"
    },
    {
        "word": "コロナ",
        "count": 1,
        "total_count": 977,
        "x": 3.846348524093628,
        "y": -17.236757278442383,
        "color": "red"
    }
]