[
    {
        "word": "明日",
        "count": 1,
        "total_count": 41,
        "x": 11.303892135620117,
        "y": -13.950044631958008,
        "color": "#3778bf"
    },
    {
        "word": "仙台",
        "count": 1,
        "total_count": 20,
        "x": 7.705498695373535,
        "y": -0.2264806032180786,
        "color": "#388004"
    },
    {
        "word": "東京",
        "count": 1,
        "total_count": 35,
        "x": 8.928055763244629,
        "y": -0.4774792790412903,
        "color": "#388004"
    },
    {
        "word": "前",
        "count": 1,
        "total_count": 47,
        "x": -2.107016086578369,
        "y": 2.122054100036621,
        "color": "#388004"
    },
    {
        "word": "コロナ",
        "count": 2,
        "total_count": 977,
        "x": 3.846348524093628,
        "y": -17.236757278442383,
        "color": "red"
    },
    {
        "word": "そう",
        "count": 1,
        "total_count": 63,
        "x": -4.626671314239502,
        "y": -11.189027786254883,
        "color": "#05ffa6"
    },
    {
        "word": "事",
        "count": 1,
        "total_count": 113,
        "x": -8.554739952087402,
        "y": 6.119753360748291,
        "color": "#388004"
    }
]