[
    {
        "word": "天然",
        "count": 1,
        "total_count": 22,
        "x": 2.846818208694458,
        "y": 1.871865153312683,
        "color": "#388004"
    },
    {
        "word": "く",
        "count": 1,
        "total_count": 14,
        "x": 0.28925514221191406,
        "y": -8.794368743896484,
        "color": "#8b3103"
    },
    {
        "word": "笑顔",
        "count": 1,
        "total_count": 82,
        "x": 1.2950809001922607,
        "y": -15.744165420532227,
        "color": "#7d7103"
    },
    {
        "word": "場所",
        "count": 1,
        "total_count": 64,
        "x": 3.8945467472076416,
        "y": 2.409726142883301,
        "color": "#388004"
    },
    {
        "word": "コロナワールド",
        "count": 1,
        "total_count": 93,
        "x": 5.272794246673584,
        "y": 1.3264681100845337,
        "color": "#388004"
    }
]