[
    {
        "word": "3月",
        "count": 2,
        "total_count": 16,
        "x": -3.257103681564331,
        "y": 7.761380672454834,
        "color": "#dc4d01"
    },
    {
        "word": "中止",
        "count": 2,
        "total_count": 53,
        "x": -5.562343597412109,
        "y": 12.10726261138916,
        "color": "#0804f9"
    },
    {
        "word": "コロナ",
        "count": 1,
        "total_count": 977,
        "x": 20.82737922668457,
        "y": 4.147772789001465,
        "color": "#acbb0d"
    },
    {
        "word": "対策",
        "count": 1,
        "total_count": 159,
        "x": -12.677927017211914,
        "y": -6.355306148529053,
        "color": "#7bfdc7"
    },
    {
        "word": "為",
        "count": 1,
        "total_count": 22,
        "x": 4.900168418884277,
        "y": -9.320230484008789,
        "color": "#a6fbb2"
    },
    {
        "word": "方",
        "count": 2,
        "total_count": 94,
        "x": 5.233116149902344,
        "y": -6.965254783630371,
        "color": "#c9d179"
    },
    {
        "word": "次",
        "count": 1,
        "total_count": 13,
        "x": 3.800776958465576,
        "y": 0.8619257211685181,
        "color": "#acc2d9"
    },
    {
        "word": "予定",
        "count": 1,
        "total_count": 30,
        "x": -2.5316450595855713,
        "y": 10.31760025024414,
        "color": "#0804f9"
    },
    {
        "word": "自分",
        "count": 1,
        "total_count": 63,
        "x": 13.5686616897583,
        "y": -1.5334210395812988,
        "color": "#4e518b"
    },
    {
        "word": "元気",
        "count": 1,
        "total_count": 13,
        "x": 16.680789947509766,
        "y": 7.017026901245117,
        "color": "#13bbaf"
    },
    {
        "word": "健康",
        "count": 1,
        "total_count": 14,
        "x": -8.677216529846191,
        "y": -10.708035469055176,
        "color": "#fcfc81"
    },
    {
        "word": "コロナウイルス",
        "count": 1,
        "total_count": 293,
        "x": -17.35605812072754,
        "y": -6.746431350708008,
        "color": "#a90308"
    }
]