[
    {
        "word": "コロナウィルス",
        "count": 1,
        "total_count": 145,
        "x": -16.906265258789062,
        "y": -6.38503885269165,
        "color": "#a90308"
    },
    {
        "word": "日本",
        "count": 1,
        "total_count": 166,
        "x": -6.898014068603516,
        "y": -1.0123347043991089,
        "color": "#befdb7"
    },
    {
        "word": "問題",
        "count": 1,
        "total_count": 41,
        "x": 1.061263918876648,
        "y": -10.530574798583984,
        "color": "#bdf6fe"
    },
    {
        "word": "体",
        "count": 1,
        "total_count": 16,
        "x": 4.605719089508057,
        "y": 2.4240121841430664,
        "color": "#acc2d9"
    },
    {
        "word": "大丈夫",
        "count": 1,
        "total_count": 33,
        "x": 16.37116813659668,
        "y": 1.5049039125442505,
        "color": "#acbb0d"
    },
    {
        "word": "方",
        "count": 1,
        "total_count": 94,
        "x": 5.233116149902344,
        "y": -6.965254783630371,
        "color": "#c9d179"
    },
    {
        "word": "話",
        "count": 1,
        "total_count": 22,
        "x": 9.155198097229004,
        "y": -1.1375492811203003,
        "color": "#bccb7a"
    }
]