[
    {
        "word": "そう",
        "count": 2,
        "total_count": 63,
        "x": -4.626671314239502,
        "y": -11.189027786254883,
        "color": "#05ffa6"
    },
    {
        "word": "自分",
        "count": 1,
        "total_count": 63,
        "x": -7.192264556884766,
        "y": -7.313666820526123,
        "color": "#05ffa6"
    },
    {
        "word": "地域",
        "count": 1,
        "total_count": 14,
        "x": -0.15155386924743652,
        "y": 5.576517581939697,
        "color": "#388004"
    },
    {
        "word": "コロナ",
        "count": 1,
        "total_count": 977,
        "x": 3.846348524093628,
        "y": -17.236757278442383,
        "color": "red"
    }
]