[
    {
        "word": "新型コロナウイルス",
        "count": 2,
        "total_count": 226,
        "x": 9.826017379760742,
        "y": 19.5113582611084,
        "color": "red"
    },
    {
        "word": "対策",
        "count": 1,
        "total_count": 159,
        "x": -4.981560230255127,
        "y": 15.757156372070312,
        "color": "red"
    },
    {
        "word": "LINE",
        "count": 2,
        "total_count": 16,
        "x": 8.299117088317871,
        "y": 11.708547592163086,
        "color": "red"
    },
    {
        "word": "何",
        "count": 1,
        "total_count": 68,
        "x": -8.305984497070312,
        "y": -5.79446268081665,
        "color": "#05ffa6"
    }
]