[
    {
        "word": "コロナウイルス",
        "count": 1,
        "total_count": 293,
        "x": 6.595101356506348,
        "y": 17.35673713684082,
        "color": "red"
    },
    {
        "word": "近く",
        "count": 1,
        "total_count": 16,
        "x": 1.136523723602295,
        "y": -1.4339321851730347,
        "color": "#388004"
    },
    {
        "word": "事",
        "count": 1,
        "total_count": 113,
        "x": -8.554739952087402,
        "y": 6.119753360748291,
        "color": "#388004"
    },
    {
        "word": "消毒",
        "count": 1,
        "total_count": 17,
        "x": -16.33595848083496,
        "y": 5.604434490203857,
        "color": "#d99b82"
    },
    {
        "word": "気",
        "count": 1,
        "total_count": 88,
        "x": -8.679996490478516,
        "y": -13.237540245056152,
        "color": "#05ffa6"
    }
]