[
    {
        "word": "中国人",
        "count": 1,
        "total_count": 41,
        "x": 1.724440574645996,
        "y": 13.03155517578125,
        "color": "#69d84f"
    },
    {
        "word": "コロナ",
        "count": 3,
        "total_count": 977,
        "x": 3.846348524093628,
        "y": -17.236757278442383,
        "color": "red"
    },
    {
        "word": "これ",
        "count": 1,
        "total_count": 69,
        "x": -6.52756404876709,
        "y": -1.6282962560653687,
        "color": "red"
    },
    {
        "word": "中国",
        "count": 1,
        "total_count": 219,
        "x": 3.0897297859191895,
        "y": 12.336210250854492,
        "color": "#69d84f"
    },
    {
        "word": "発症",
        "count": 1,
        "total_count": 18,
        "x": -11.943520545959473,
        "y": 13.027159690856934,
        "color": "#a6c875"
    },
    {
        "word": "前",
        "count": 1,
        "total_count": 47,
        "x": -2.107016086578369,
        "y": 2.122054100036621,
        "color": "#388004"
    },
    {
        "word": "日本",
        "count": 1,
        "total_count": 166,
        "x": 1.4311420917510986,
        "y": 11.37730598449707,
        "color": "#69d84f"
    },
    {
        "word": "人",
        "count": 2,
        "total_count": 216,
        "x": -9.302090644836426,
        "y": -2.933377265930176,
        "color": "red"
    },
    {
        "word": "わけ",
        "count": 1,
        "total_count": 20,
        "x": -7.061621189117432,
        "y": 0.9121825695037842,
        "color": "#388004"
    },
    {
        "word": "みたい",
        "count": 1,
        "total_count": 45,
        "x": -5.0331854820251465,
        "y": -13.050077438354492,
        "color": "#05ffa6"
    },
    {
        "word": "自分",
        "count": 1,
        "total_count": 63,
        "x": -7.192264556884766,
        "y": -7.313666820526123,
        "color": "#05ffa6"
    },
    {
        "word": "事",
        "count": 1,
        "total_count": 113,
        "x": -8.554739952087402,
        "y": 6.119753360748291,
        "color": "#388004"
    },
    {
        "word": "免疫力",
        "count": 1,
        "total_count": 14,
        "x": -13.809158325195312,
        "y": 7.11320161819458,
        "color": "red"
    }
]