[
    {
        "word": "新型コロナウィルス",
        "count": 1,
        "total_count": 83,
        "x": 8.784623146057129,
        "y": 16.100282669067383,
        "color": "#acc2d9"
    },
    {
        "word": "会社",
        "count": 1,
        "total_count": 23,
        "x": 3.6516125202178955,
        "y": -1.8548256158828735,
        "color": "#388004"
    },
    {
        "word": "インフル",
        "count": 1,
        "total_count": 25,
        "x": -14.767908096313477,
        "y": 11.824165344238281,
        "color": "#a6c875"
    },
    {
        "word": "対策",
        "count": 1,
        "total_count": 159,
        "x": -4.981560230255127,
        "y": 15.757156372070312,
        "color": "red"
    },
    {
        "word": "いい",
        "count": 1,
        "total_count": 77,
        "x": -9.006982803344727,
        "y": -10.00387954711914,
        "color": "#05ffa6"
    },
    {
        "word": "病院",
        "count": 1,
        "total_count": 44,
        "x": -8.97205924987793,
        "y": 12.335251808166504,
        "color": "#a6c875"
    }
]