[
    {
        "word": "ない",
        "count": 2,
        "total_count": 165,
        "x": -12.52199935913086,
        "y": -4.814731597900391,
        "color": "#65ab7c"
    },
    {
        "word": "コロナウィルス",
        "count": 1,
        "total_count": 145,
        "x": 6.935372829437256,
        "y": 16.993133544921875,
        "color": "red"
    },
    {
        "word": "以上",
        "count": 1,
        "total_count": 29,
        "x": 0.2669301927089691,
        "y": -1.7513492107391357,
        "color": "#388004"
    },
    {
        "word": "笑顔",
        "count": 1,
        "total_count": 82,
        "x": 1.2950809001922607,
        "y": -15.744165420532227,
        "color": "#7d7103"
    },
    {
        "word": "自分",
        "count": 1,
        "total_count": 63,
        "x": -7.192264556884766,
        "y": -7.313666820526123,
        "color": "#05ffa6"
    },
    {
        "word": "マスク",
        "count": 1,
        "total_count": 140,
        "x": -17.223421096801758,
        "y": 6.508975505828857,
        "color": "#d99b82"
    },
    {
        "word": "そう",
        "count": 1,
        "total_count": 63,
        "x": -4.626671314239502,
        "y": -11.189027786254883,
        "color": "#05ffa6"
    }
]