[
    {
        "word": "コロナ",
        "count": 1,
        "total_count": 977,
        "x": 20.82737922668457,
        "y": 4.147772789001465,
        "color": "#acbb0d"
    },
    {
        "word": "学校",
        "count": 1,
        "total_count": 13,
        "x": -2.1743130683898926,
        "y": 5.176786422729492,
        "color": "#dc4d01"
    },
    {
        "word": "休み",
        "count": 1,
        "total_count": 25,
        "x": 5.069252014160156,
        "y": 15.461215019226074,
        "color": "#054907"
    },
    {
        "word": "何",
        "count": 1,
        "total_count": 68,
        "x": 10.718135833740234,
        "y": -3.0071871280670166,
        "color": "#ff964f"
    },
    {
        "word": "そう",
        "count": 1,
        "total_count": 63,
        "x": 15.321756362915039,
        "y": 0.5994836091995239,
        "color": "#4e518b"
    },
    {
        "word": "先",
        "count": 1,
        "total_count": 19,
        "x": 4.476838111877441,
        "y": -0.9294489622116089,
        "color": "#7ea07a"
    }
]