[
    {
        "word": "武漢",
        "count": 1,
        "total_count": 98,
        "x": -9.833353996276855,
        "y": -2.530468225479126,
        "color": "#b75203"
    },
    {
        "word": "市",
        "count": 1,
        "total_count": 24,
        "x": -0.4258944094181061,
        "y": 4.005334854125977,
        "color": "#fafe4b"
    },
    {
        "word": "方々",
        "count": 1,
        "total_count": 15,
        "x": 0.9489143490791321,
        "y": -3.932175397872925,
        "color": "#6ecb3c"
    },
    {
        "word": "日本",
        "count": 1,
        "total_count": 166,
        "x": -6.898014068603516,
        "y": -1.0123347043991089,
        "color": "#befdb7"
    },
    {
        "word": "感染",
        "count": 1,
        "total_count": 182,
        "x": -15.474895477294922,
        "y": -0.1394830197095871,
        "color": "#430541"
    },
    {
        "word": "新型肺炎",
        "count": 1,
        "total_count": 233,
        "x": -14.604652404785156,
        "y": -3.465946912765503,
        "color": "#2bb179"
    },
    {
        "word": "人",
        "count": 1,
        "total_count": 216,
        "x": -0.2386651188135147,
        "y": -7.278883457183838,
        "color": "#ff6cb5"
    },
    {
        "word": "一番",
        "count": 1,
        "total_count": 13,
        "x": 10.330925941467285,
        "y": 0.6577735543251038,
        "color": "#fff39a"
    },
    {
        "word": "日本人",
        "count": 1,
        "total_count": 18,
        "x": -8.46033763885498,
        "y": -0.936541736125946,
        "color": "#befdb7"
    },
    {
        "word": "方",
        "count": 1,
        "total_count": 94,
        "x": 5.233116149902344,
        "y": -6.965254783630371,
        "color": "#c9d179"
    },
    {
        "word": "いい",
        "count": 1,
        "total_count": 77,
        "x": 16.443626403808594,
        "y": -2.109023094177246,
        "color": "#4efd54"
    }
]