[
    {
        "word": "新型コロナウイルス",
        "count": 1,
        "total_count": 226,
        "x": 9.826017379760742,
        "y": 19.5113582611084,
        "color": "red"
    },
    {
        "word": "インフル",
        "count": 1,
        "total_count": 25,
        "x": -14.767908096313477,
        "y": 11.824165344238281,
        "color": "#a6c875"
    },
    {
        "word": "経済",
        "count": 1,
        "total_count": 18,
        "x": -1.074376106262207,
        "y": 10.760099411010742,
        "color": "#69d84f"
    },
    {
        "word": "医療",
        "count": 1,
        "total_count": 16,
        "x": -7.828829765319824,
        "y": 13.065840721130371,
        "color": "#a6c875"
    },
    {
        "word": "者",
        "count": 1,
        "total_count": 32,
        "x": -4.043076038360596,
        "y": 6.7805585861206055,
        "color": "#c9d179"
    },
    {
        "word": "時",
        "count": 1,
        "total_count": 55,
        "x": -1.7581535577774048,
        "y": 3.318898916244507,
        "color": "#388004"
    },
    {
        "word": "よう",
        "count": 1,
        "total_count": 118,
        "x": 18.377994537353516,
        "y": 2.7947516441345215,
        "color": "red"
    }
]