[
    {
        "word": "達",
        "count": 1,
        "total_count": 17,
        "x": 1.1790248155593872,
        "y": -2.850152015686035,
        "color": "#6ecb3c"
    },
    {
        "word": "家族",
        "count": 1,
        "total_count": 16,
        "x": -0.08541303128004074,
        "y": -4.900813102722168,
        "color": "#6ecb3c"
    },
    {
        "word": "コロナ",
        "count": 1,
        "total_count": 977,
        "x": 20.82737922668457,
        "y": 4.147772789001465,
        "color": "#acbb0d"
    },
    {
        "word": "騒動",
        "count": 1,
        "total_count": 14,
        "x": 10.050256729125977,
        "y": -12.276451110839844,
        "color": "#475f94"
    },
    {
        "word": "場所",
        "count": 1,
        "total_count": 64,
        "x": 6.266230583190918,
        "y": -3.72700834274292,
        "color": "#bccb7a"
    }
]