[
    {
        "word": "さん",
        "count": 1,
        "total_count": 121,
        "x": 14.270416259765625,
        "y": 7.686995506286621,
        "color": "#cb9d06"
    },
    {
        "word": "コロナ",
        "count": 1,
        "total_count": 977,
        "x": 20.82737922668457,
        "y": 4.147772789001465,
        "color": "#acbb0d"
    },
    {
        "word": "情報",
        "count": 1,
        "total_count": 38,
        "x": -2.3098607063293457,
        "y": -8.41650676727295,
        "color": "#ff6cb5"
    },
    {
        "word": "自分",
        "count": 1,
        "total_count": 63,
        "x": 13.5686616897583,
        "y": -1.5334210395812988,
        "color": "#4e518b"
    },
    {
        "word": "こと",
        "count": 1,
        "total_count": 160,
        "x": 5.831828594207764,
        "y": -10.66402530670166,
        "color": "#a6fbb2"
    }
]